{"version":1,"resource":"file:///Users/pastrysweet/Documents/MATLAB/%E7%AC%AC%E5%9B%9B%E6%AC%A1%E4%B8%8A%E6%9C%BA/Q1.m","entries":[{"id":"LB4u.m","timestamp":1733121925312},{"id":"n28j.m","timestamp":1733121988535},{"id":"z9Mc.m","timestamp":1733124594916},{"id":"iqDa.m","timestamp":1733124625940},{"id":"tZrU.m","timestamp":1733124646178},{"id":"B7Pl.m","timestamp":1733124663286},{"id":"GpFC.m","timestamp":1733124685797},{"id":"N97W.m","timestamp":1733127993084},{"id":"312u.m","timestamp":1733128008313}]}