{"version":1,"resource":"file:///Users/pastrysweet/Documents/GitHub/raman/.gitignore","entries":[{"id":"GAJm","timestamp":1744596026230},{"id":"L47c","timestamp":1744596066811},{"id":"I8oV","timestamp":1744596099298},{"id":"T9hv","timestamp":1744596138443},{"id":"Irgm","timestamp":1744596199707},{"id":"XcYb","timestamp":1744596235599},{"id":"Ml1M","timestamp":1744596265206},{"id":"j6p9","timestamp":1744596296313},{"id":"HTdo","timestamp":1744596367405},{"id":"ZG9r","timestamp":1744596406308},{"id":"xPGG","timestamp":1744596498395},{"id":"PHRO","timestamp":1744596547815},{"id":"w1ix","timestamp":1744596580806},{"id":"Qccc","timestamp":1744596598990},{"id":"p049","timestamp":1744597219455},{"id":"gH57","source":"undoRedo.source","timestamp":1744597222042},{"id":"OzZh","timestamp":1744597246810}]}